EngineerAi/EngineerAi.py
EngineerAi/__init__.py
engineerai-2.7.dist-info/LICENSE
engineerai-2.7.dist-info/METADATA
engineerai-2.7.dist-info/WHEEL
engineerai-2.7.dist-info/top_level.txt
engineerai-2.7.dist-info/RECORD
