Metadata-Version: 2.1
Name: engineerai
Version: 2.7
Summary: Ai Tools for developers
Author: Engineer Man
Author-email: MrAws.developer@gmail.com
Keywords: python,ai,speech,text,eng-tools,eng-ai,pydub,pyaudio,numpy,opencv,pillow,pandas,sqlite3,openpyxl
Classifier: Development Status :: 1 - Planning
Classifier: Intended Audience :: Developers
Classifier: Programming Language :: Python :: 3
Classifier: Operating System :: Unix
Classifier: Operating System :: MacOS :: MacOS X
Classifier: Operating System :: Microsoft :: Windows
Requires-Python: ~=3.6
License-File: LICENSE
Requires-Dist: requests
Requires-Dist: SpeechRecognition
Requires-Dist: openai
